sphinx_autodoc_future_annotations/__init__.py
sphinx_autodoc_future_annotations-0.1.3.dist-info/LICENSE.txt
sphinx_autodoc_future_annotations-0.1.3.dist-info/METADATA
sphinx_autodoc_future_annotations-0.1.3.dist-info/WHEEL
sphinx_autodoc_future_annotations-0.1.3.dist-info/top_level.txt
sphinx_autodoc_future_annotations-0.1.3.dist-info/RECORD
